<?xml version="1.0"?>
<Flows>
	<item src="00" dif="NET">
		<flow dst="A" />
		<flow dst="01" />
	</item> 
	<item src="01" dif="NET">
		<flow dst="02" />
	</item> 
	<item src="02" dif="NET">
		<flow dst="03" />
	</item> 
	<item src="03" dif="NET">
		<flow dst="B" />
	</item> 
	
	
	<item src="30" dif="NET">
		<flow dst="C" />
		<flow dst="31" />
	</item> 
	<item src="31" dif="NET">
		<flow dst="21" />
	</item> 
	<item src="21" dif="NET">
		<flow dst="22" />
	</item> 
	<item src="22" dif="NET">
		<flow dst="32" />
	</item> 
	<item src="32" dif="NET">
		<flow dst="33" />
	</item> 
	<item src="33" dif="NET">
		<flow dst="D" />
	</item> 
</Flows>
